dirba/__init__.py
dirba/logging_utils.py
dirba/models/__init__.py
dirba/models/abc.py
dirba/models/dambo.py
dirba/runners/__init__.py
dirba/runners/api_runner.py
dirba/runners/kafka_runners/__init__.py
dirba/runners/kafka_runners/abstract_runner.py
dirba/runners/kafka_runners/consumer.py
dirba/runners/kafka_runners/producer.py
dirba/runners/kafka_runners/runner.py
dirba/runners/kafka_runners/shared.py
dirba/runners/kafka_runners/strict_runner.py
dirba/runners/kafka_runners/topic_schemas.py
dirba/utils/__init__.py
dirba/utils/catalogs/__init__.py
dirba/utils/catalogs/abc.py
dirba/utils/catalogs/category.py
dirba/utils/catalogs/exceptions.py
dirba/utils/data_loader/__init__.py
dirba/utils/data_loader/abc.py
dirba/utils/data_loader/exceptions.py
dirba/utils/data_loader/html.py
dirba/utils/data_loader/image.py
dirba/utils/data_loader/text.py
dirba/utils/metrics/__init__.py
dirba/utils/metrics/abc.py
dirba/utils/metrics/material_metric.py
dirba/utils/metrics/prometheus_exporter.py
dirba/validation/__init__.py
dirba/validation/dataset.py
dirba/validation/metrics.py
dirba/validation/utils.py
dirba/validation/validation.py
dirba-0.1.3.dist-info/METADATA
dirba-0.1.3.dist-info/WHEEL
dirba-0.1.3.dist-info/top_level.txt
dirba-0.1.3.dist-info/RECORD
