Metadata-Version: 2.1
Name: dirba
Version: 0.1.3
Summary: Small ML boilerplate
Home-page: https://gitlab.uriit.ru/CIAS/dirba
Author: Mansur Izert
Author-email: izertmi@uriit.ru
License: UNKNOWN
Platform: UNKNOWN
Classifier: Programming Language :: Python :: 3
Classifier: License :: OSI Approved :: MIT License
Classifier: Operating System :: OS Independent
Requires-Python: >=3.6
Requires-Dist: requests
Requires-Dist: fastapi (>=0.63.0)
Requires-Dist: pydantic (>=1.8.1)
Requires-Dist: python-multipart (>=0.0.5)
Requires-Dist: uvicorn (>=0.11.3)
Requires-Dist: aiomisc (>=12.1.0)
Requires-Dist: aiohttp (<4.0.0,>3.7.0)
Requires-Dist: aiohttp-asgi (>=0.3.1)
Requires-Dist: orjson (>=3.5.1)
Requires-Dist: sentry-sdk (>=0.19.0)
Requires-Dist: cachetools (>=4.2.1)
Requires-Dist: asyncache (>=0.1.1)
Requires-Dist: prometheus-client (<0.11.0,>=0.10.1)
Provides-Extra: kafka
Requires-Dist: aiokafka (<0.8.0,>=0.7.0) ; extra == 'kafka'
Provides-Extra: validation
Requires-Dist: scikit-learn (<0.24,>=0.21.0.1) ; extra == 'validation'
Requires-Dist: pandas (>=1.0.1) ; extra == 'validation'
